aufwaermteil/MealyMaschine.v
module MealyPattern(
	input        clock,
	input        i,
	output [1:0] o
);

//HIER WAR DAS TODO, FALLS ES ZU FEHLERN KOMMT :)
reg ff1, ff2;

always @(posedge clock)
		begin
			ff1 <= i;
			ff2 <= ff1;
			$display("cycle");
			$display(i);
			
			$display(ff1);
			$display(ff2);
			
			$display("generated output");
			$display("pattern 111 (o[1])");
			$display(ff1 & ff2 & i);
			$display("pattern 001 (o[0])");
			$display(!ff1 & !ff2 & i);
			$display("\n");
			
		end
	/*assign o[0] = (!ff1 & !ff2 & i) ? 1'b1 : 1'b0;
	assign o[1] = (ff1 & ff2 & i) ? 1'b1 : 1'b0;*/

	assign o = (i == 1'b0) ? 2'b0 : ((ff1 != ff2) ? 2'b0 : ((ff1 == 1'b1) ? 2'b10 : 2'b01));

endmodule

module MealyPatternTestbench();
//HIER WAR DAS TODO, FALLS ES ZU FEHLERN KOMMT :)
reg clk;
reg [9:0] inp;
reg currInp;
reg [3:0] c;
wire [1:0] out;

//initialisieren	
initial 
	begin
		inp = 10'b1001100111;
		clk = 0;
		c = 0;
		$dumpfile("mealy.vcd");
		$dumpvars;
	end

	//die clock
always 
	begin
		clk <= 1'b1; #5; clk <= 1'b0; #5;
	end

	MealyPattern machine(.clock(clk), .i(currInp), .o(out));	

	//eigentlicher Tester (einfaches matchen)
	initial
	begin
		currInp = 1'b0;
		#20
		$display("\n start \n");
		currInp = inp[0];
		#10;
		$display(out);
		if (out[0] != 0 | out[1] != 0)
			$display("fault on 0");
		currInp = inp[1];
		#10;
		$display(out);
		if (out[0] == 1 | out[1] == 1)
			$display("fault on 1");
		currInp = inp[2];
		#10;
		$display(out);
		if (out[0] != 0 | out[1] != 1)
			$display("fault on 2");
		currInp = inp[3];
		#10;
		$display(out);
		if (out[0] != 0 | out[1] != 1)
			$display("fault on 3");
		currInp = inp[4];
		#10;
		$display(out);
		if (out[0] != 0 | out[1] != 0)
			$display("fault on 3");
      currInp = inp[5];
		#10;
		$display(out);
		if (out[0] != 0 | out[1] != 0)
			$display("fault on 4");
      currInp = inp[6];
		#10;
		$display(out);
		if (out[0] != 1 | out[1] != 0)
			$display("fault on 5");
		currInp = inp[7];
		#10;
		$display(out);
		if (out[0] != 0 | out[1] != 0)
			$display("fault on 6");
      currInp = inp[8];
		#10;
		$display(out);
		if (out[0] != 0 | out[1] != 0)
			$display("fault on 7");
      currInp = inp[9];
		#10;
		$display(out);
		if (out[0] != 1 | out[1] != 0)
			$display("fault on 9");
		$finish;
	end


endmodule

aufwaermteil/mealy.vcd
$date
	Thu Jun 25 11:50:52 2020
$end
$version
	Icarus Verilog
$end
$timescale
	1s
$end
$scope module MealyPatternTestbench $end
$var wire 2 ! out [1:0] $end
$var reg 4 " c [3:0] $end
$var reg 1 # clk $end
$var reg 1 $ currInp $end
$var reg 10 % inp [9:0] $end
$scope module machine $end
$var wire 1 # clock $end
$var wire 1 $ i $end
$var wire 2 & o [1:0] $end
$var reg 1 ' ff1 $end
$var reg 1 ( ff2 $end
$upscope $end
$upscope $end
$enddefinitions $end
#0
$dumpvars
x(
0'
b0 &
b1001100111 %
0$
1#
b0 "
b0 !
$end
#5
0#
#10
0(
1#
#15
0#
#20
1'
1#
b0 !
b0 &
1$
#25
0#
#30
b10 !
b10 &
1(
1#
#35
0#
#40
1#
#45
0#
#50
0'
1#
b0 !
b0 &
0$
#55
0#
#60
0(
1#
#65
0#
#70
1'
1#
b0 !
b0 &
1$
#75
0#
#80
b10 !
b10 &
1(
1#
#85
0#
#90
0'
1#
b0 !
b0 &
0$
#95
0#
#100
0(
1#
#105
0#
#110
1'
1#
b0 !
b0 &
1$
#115
0#
#120
b10 !
b10 &
1(
1#
